scdiffeq_plots/__init__.py
scdiffeq_plots/_color_map_plot.py
scdiffeq_plots/_discretized_color_map.py
scdiffeq_plots/_loss_viz_ax.py
scdiffeq_plots/_temporal_cmap.py
scdiffeq_plots/_temporal_colormap.py
scdiffeq_plots/_temporal_distances.py
scdiffeq_plots/core/__init__.py
scdiffeq_plots/core/_plot.py
scdiffeq_plots/core/_plot_dimensions.py
scdiffeq_plots/core/_style_spines.py
scdiffeq_plots/utils/__init__.py
scdiffeq_plots/utils/_abc_parse.py
scdiffeq_plots/utils/_extract_func_kwargs.py
scdiffeq_plots/utils/_info_message.py
scdiffeq_plots-0.0.1rc2.dist-info/LICENSE
scdiffeq_plots-0.0.1rc2.dist-info/METADATA
scdiffeq_plots-0.0.1rc2.dist-info/WHEEL
scdiffeq_plots-0.0.1rc2.dist-info/top_level.txt
scdiffeq_plots-0.0.1rc2.dist-info/RECORD
