Metadata-Version: 2.1
Name: scdiffeq-plots
Version: 0.0.1rc2
Summary: Plotting functions associated wtih analyses from scDiffEq
Home-page: https://github.com/scDiffEq/scdiffeq-plots
Author: Michael E. Vinyard - Harvard University - Massachussetts General Hospital - Broad Institute of MIT and Harvard
Author-email: mvinyard@broadinstitute.org
License: MIT
Classifier: Development Status :: 2 - Pre-Alpha
Classifier: Programming Language :: Python :: 3.9
Classifier: Intended Audience :: Science/Research
Classifier: Topic :: Scientific/Engineering :: Bio-Informatics
Requires-Python: >3.9.0
License-File: LICENSE
Requires-Dist: matplotlib (>=3.7.1)
